extend_py/__init__.py
extend_py/extend_py.py
extend_py-1.0.4.dist-info/LICENSE
extend_py-1.0.4.dist-info/METADATA
extend_py-1.0.4.dist-info/WHEEL
extend_py-1.0.4.dist-info/top_level.txt
extend_py-1.0.4.dist-info/RECORD
