Metadata-Version: 2.1
Name: extend-py
Version: 1.0.4
Summary: This is a extc
Home-page: https://gitee.com/bailiyiyun/extc-package
Author: bailiyiyun
Author-email: 995440065@qq.com
License: UNKNOWN
Platform: UNKNOWN
Classifier: Programming Language :: Python :: 3
